<?xml version="1.0" encoding="UTF-8"?><apiPackage id="DisplayApplication.CustomSkins"><apiName>DisplayApplication.CustomSkins</apiName><apiDetail/><apiClassifier id="DisplayApplication.CustomSkins:CustomForwardButtonSkin"><apiName>CustomForwardButtonSkin</apiName><shortdesc>The default skin class for the Spark Button component.</shortdesc><prolog><asMetadata><apiVersion><apiLanguage version="3.0"/><apiPlatform description="" name="Flash" version="10"/><apiPlatform description="" name="AIR" version="1.5"/><apiTool description="" name="Flex" version="4"/></apiVersion><DefaultProperty name="mxmlContent"/></asMetadata></prolog><apiClassifierDetail><apiClassifierDef><apiAccess value="public"/><apiStatic/><apiBaseInterface>mx.binding:IBindingClient</apiBaseInterface><apiBaseInterface>mx.core:IStateClient2</apiBaseInterface><apiBaseClassifier>spark.skins:SparkSkin</apiBaseClassifier></apiClassifierDef><apiDesc>The default skin class for the Spark Button component.  
</apiDesc></apiClassifierDetail><related-links><link href="" invalidHref="spark.components.Button.xml"><linktext>spark.components.Button</linktext></link></related-links><apiConstructor id="DisplayApplication.CustomSkins:CustomForwardButtonSkin:CustomForwardButtonSkin"><apiName>CustomForwardButtonSkin</apiName><shortdesc>Constructor.</shortdesc><prolog/><apiConstructorDetail><apiConstructorDef><apiAccess value="public"/></apiConstructorDef><apiDesc>Constructor.</apiDesc></apiConstructorDetail></apiConstructor><apiValue id="DisplayApplication.CustomSkins:CustomForwardButtonSkin:hostComponent"><apiName>hostComponent</apiName><shortdesc conref="spark.skins.spark.ApplicationSkin#hostComponent"> 
		</shortdesc><prolog/><apiValueDetail><apiValueDef><apiProperty isBindable="true" name="Bindable"/><apiAccess value="public"/><apiDynamic/><apiType value="spark.components:Button"/></apiValueDef><apiDesc conref="spark.skins.spark.ApplicationSkin#hostComponent"> 
		</apiDesc></apiValueDetail></apiValue><apiValue id="DisplayApplication.CustomSkins:CustomForwardButtonSkin:labelDisplay"><apiName>labelDisplay</apiName><shortdesc/><prolog/><apiValueDetail><apiValueDef><apiProperty isBindable="true" name="Bindable"/><apiAccess value="public"/><apiDynamic/><apiType value="spark.components:Label"/></apiValueDef><apiDesc></apiDesc></apiValueDetail></apiValue></apiClassifier><apiClassifier id="DisplayApplication.CustomSkins:CustomSoundButtonSkin"><apiName>CustomSoundButtonSkin</apiName><shortdesc>The default skin class for the Spark Button component.</shortdesc><prolog><asMetadata><apiVersion><apiLanguage version="3.0"/><apiPlatform description="" name="Flash" version="10"/><apiPlatform description="" name="AIR" version="1.5"/><apiTool description="" name="Flex" version="4"/></apiVersion><DefaultProperty name="mxmlContent"/></asMetadata></prolog><apiClassifierDetail><apiClassifierDef><apiAccess value="public"/><apiStatic/><apiBaseInterface>mx.binding:IBindingClient</apiBaseInterface><apiBaseInterface>mx.core:IStateClient2</apiBaseInterface><apiBaseClassifier>spark.skins:SparkSkin</apiBaseClassifier></apiClassifierDef><apiDesc>The default skin class for the Spark Button component.  
</apiDesc></apiClassifierDetail><related-links><link href="" invalidHref="spark.components.Button.xml"><linktext>spark.components.Button</linktext></link></related-links><apiConstructor id="DisplayApplication.CustomSkins:CustomSoundButtonSkin:CustomSoundButtonSkin"><apiName>CustomSoundButtonSkin</apiName><shortdesc>Constructor.</shortdesc><prolog/><apiConstructorDetail><apiConstructorDef><apiAccess value="public"/></apiConstructorDef><apiDesc>Constructor.</apiDesc></apiConstructorDetail></apiConstructor><apiValue id="DisplayApplication.CustomSkins:CustomSoundButtonSkin:hostComponent"><apiName>hostComponent</apiName><shortdesc conref="spark.skins.spark.ApplicationSkin#hostComponent"> 
		</shortdesc><prolog/><apiValueDetail><apiValueDef><apiProperty isBindable="true" name="Bindable"/><apiAccess value="public"/><apiDynamic/><apiType value="spark.components:Button"/></apiValueDef><apiDesc conref="spark.skins.spark.ApplicationSkin#hostComponent"> 
		</apiDesc></apiValueDetail></apiValue></apiClassifier><apiClassifier id="DisplayApplication.CustomSkins:CustomVideoPlayerSkin"><apiName>CustomVideoPlayerSkin</apiName><shortdesc>The default skin class for the Spark VideoPlayer component.</shortdesc><prolog><asMetadata><apiVersion><apiLanguage version="3.0"/><apiPlatform description="" name="Flash" version="10"/><apiPlatform description="" name="AIR" version="1.5"/><apiTool description="" name="Flex" version="4"/></apiVersion><DefaultProperty name="mxmlContent"/></asMetadata></prolog><apiClassifierDetail><apiClassifierDef><apiAccess value="public"/><apiStatic/><apiBaseInterface>mx.binding:IBindingClient</apiBaseInterface><apiBaseInterface>mx.core:IStateClient2</apiBaseInterface><apiBaseClassifier>spark.skins:SparkSkin</apiBaseClassifier></apiClassifierDef><apiDesc>The default skin class for the Spark VideoPlayer component.  
     </apiDesc></apiClassifierDetail><related-links><link href="" invalidHref="spark.components.VideoPlayer.xml"><linktext>spark.components.VideoPlayer</linktext></link></related-links><apiConstructor id="DisplayApplication.CustomSkins:CustomVideoPlayerSkin:CustomVideoPlayerSkin"><apiName>CustomVideoPlayerSkin</apiName><shortdesc>Constructor.</shortdesc><prolog/><apiConstructorDetail><apiConstructorDef><apiAccess value="public"/></apiConstructorDef><apiDesc>Constructor.</apiDesc></apiConstructorDetail></apiConstructor><apiValue id="DisplayApplication.CustomSkins:CustomVideoPlayerSkin:clippedGroup"><apiName>clippedGroup</apiName><shortdesc>Video and player controls are clipped if they exceed the size of the 
          component, but the drop shadow above is not clipped and sizes to the component.</shortdesc><prolog/><apiValueDetail><apiValueDef><apiProperty isBindable="true" name="Bindable"/><apiAccess value="public"/><apiDynamic/><apiType value="spark.components:Group"/></apiValueDef><apiDesc>Video and player controls are clipped if they exceed the size of the 
          component, but the drop shadow above is not clipped and sizes to the component.
          We also set verticalScrollPosition so that when we do clip, rather than clipping  
          off the bottom first, we clip off the top fist.  This is so the player controls 
          are still visible when we start clipping.</apiDesc></apiValueDetail></apiValue><apiValue id="DisplayApplication.CustomSkins:CustomVideoPlayerSkin:currentTimeDisplay"><apiName>currentTimeDisplay</apiName><shortdesc conref="spark.components.VideoPlayer#currentTimeDisplay"/><prolog/><apiValueDetail><apiValueDef><apiProperty isBindable="true" name="Bindable"/><apiAccess value="public"/><apiDynamic/><apiType value="spark.components:Label"/></apiValueDef><apiDesc conref="spark.components.VideoPlayer#currentTimeDisplay"></apiDesc></apiValueDetail></apiValue><apiValue id="DisplayApplication.CustomSkins:CustomVideoPlayerSkin:durationDisplay"><apiName>durationDisplay</apiName><shortdesc conref="spark.components.VideoPlayer#durationDisplay"/><prolog/><apiValueDetail><apiValueDef><apiProperty isBindable="true" name="Bindable"/><apiAccess value="public"/><apiDynamic/><apiType value="spark.components:Label"/></apiValueDef><apiDesc conref="spark.components.VideoPlayer#durationDisplay"></apiDesc></apiValueDetail></apiValue><apiValue id="DisplayApplication.CustomSkins:CustomVideoPlayerSkin:hostComponent"><apiName>hostComponent</apiName><shortdesc conref="spark.skins.spark.ApplicationSkin#hostComponent"> 
         </shortdesc><prolog/><apiValueDetail><apiValueDef><apiProperty isBindable="true" name="Bindable"/><apiAccess value="public"/><apiDynamic/><apiType value="spark.components:VideoPlayer"/></apiValueDef><apiDesc conref="spark.skins.spark.ApplicationSkin#hostComponent"> 
         </apiDesc></apiValueDetail></apiValue><apiValue id="DisplayApplication.CustomSkins:CustomVideoPlayerSkin:playPauseButton"><apiName>playPauseButton</apiName><shortdesc conref="spark.components.VideoPlayer#playPauseButton"/><prolog/><apiValueDetail><apiValueDef><apiProperty isBindable="true" name="Bindable"/><apiAccess value="public"/><apiDynamic/><apiType value="spark.components:ToggleButton"/></apiValueDef><apiDesc conref="spark.components.VideoPlayer#playPauseButton"></apiDesc></apiValueDetail></apiValue><apiValue id="DisplayApplication.CustomSkins:CustomVideoPlayerSkin:playerControls"><apiName>playerControls</apiName><shortdesc conref="spark.components.VideoPlayer#playerControls"/><prolog/><apiValueDetail><apiValueDef><apiProperty isBindable="true" name="Bindable"/><apiAccess value="public"/><apiDynamic/><apiType value="spark.components:Group"/></apiValueDef><apiDesc conref="spark.components.VideoPlayer#playerControls"></apiDesc></apiValueDetail></apiValue><apiValue id="DisplayApplication.CustomSkins:CustomVideoPlayerSkin:scrubBar"><apiName>scrubBar</apiName><shortdesc conref="spark.components.VideoPlayer#scrubBar"/><prolog/><apiValueDetail><apiValueDef><apiProperty isBindable="true" name="Bindable"/><apiAccess value="public"/><apiDynamic/><apiType value="spark.components.mediaClasses:ScrubBar"/></apiValueDef><apiDesc conref="spark.components.VideoPlayer#scrubBar"></apiDesc></apiValueDetail></apiValue><apiValue id="DisplayApplication.CustomSkins:CustomVideoPlayerSkin:videoDisplay"><apiName>videoDisplay</apiName><shortdesc conref="spark.components.VideoPlayer#videoDisplay"/><prolog/><apiValueDetail><apiValueDef><apiProperty isBindable="true" name="Bindable"/><apiAccess value="public"/><apiDynamic/><apiType value="spark.components:VideoDisplay"/></apiValueDef><apiDesc conref="spark.components.VideoPlayer#videoDisplay"></apiDesc></apiValueDetail></apiValue><apiValue id="DisplayApplication.CustomSkins:CustomVideoPlayerSkin:volumeBar"><apiName>volumeBar</apiName><shortdesc conref="spark.components.VideoPlayer#volumeBar"/><prolog/><apiValueDetail><apiValueDef><apiProperty isBindable="true" name="Bindable"/><apiAccess value="public"/><apiDynamic/><apiType value="spark.components.mediaClasses:VolumeBar"/></apiValueDef><apiDesc conref="spark.components.VideoPlayer#volumeBar"></apiDesc></apiValueDetail></apiValue></apiClassifier><apiClassifier id="DisplayApplication.CustomSkins:CustomButtonSkin"><apiName>CustomButtonSkin</apiName><shortdesc>The default skin class for the Spark Button component.</shortdesc><prolog><asMetadata><apiVersion><apiLanguage version="3.0"/><apiPlatform description="" name="Flash" version="10"/><apiPlatform description="" name="AIR" version="1.5"/><apiTool description="" name="Flex" version="4"/></apiVersion><DefaultProperty name="mxmlContent"/></asMetadata></prolog><apiClassifierDetail><apiClassifierDef><apiAccess value="public"/><apiStatic/><apiBaseInterface>mx.binding:IBindingClient</apiBaseInterface><apiBaseInterface>mx.core:IStateClient2</apiBaseInterface><apiBaseClassifier>spark.skins:SparkSkin</apiBaseClassifier></apiClassifierDef><apiDesc>The default skin class for the Spark Button component.  
</apiDesc></apiClassifierDetail><related-links><link href="" invalidHref="spark.components.Button.xml"><linktext>spark.components.Button</linktext></link></related-links><apiConstructor id="DisplayApplication.CustomSkins:CustomButtonSkin:CustomButtonSkin"><apiName>CustomButtonSkin</apiName><shortdesc>Constructor.</shortdesc><prolog/><apiConstructorDetail><apiConstructorDef><apiAccess value="public"/></apiConstructorDef><apiDesc>Constructor.</apiDesc></apiConstructorDetail></apiConstructor><apiValue id="DisplayApplication.CustomSkins:CustomButtonSkin:hostComponent"><apiName>hostComponent</apiName><shortdesc conref="spark.skins.spark.ApplicationSkin#hostComponent"> 
		</shortdesc><prolog/><apiValueDetail><apiValueDef><apiProperty isBindable="true" name="Bindable"/><apiAccess value="public"/><apiDynamic/><apiType value="spark.components:Button"/></apiValueDef><apiDesc conref="spark.skins.spark.ApplicationSkin#hostComponent"> 
		</apiDesc></apiValueDetail></apiValue><apiValue id="DisplayApplication.CustomSkins:CustomButtonSkin:labelDisplay"><apiName>labelDisplay</apiName><shortdesc/><prolog/><apiValueDetail><apiValueDef><apiProperty isBindable="true" name="Bindable"/><apiAccess value="public"/><apiDynamic/><apiType value="spark.components:Label"/></apiValueDef><apiDesc></apiDesc></apiValueDetail></apiValue></apiClassifier><apiClassifier id="DisplayApplication.CustomSkins:CustomStartButtonSkin"><apiName>CustomStartButtonSkin</apiName><shortdesc>The default skin class for the Spark Button component.</shortdesc><prolog><asMetadata><apiVersion><apiLanguage version="3.0"/><apiPlatform description="" name="Flash" version="10"/><apiPlatform description="" name="AIR" version="1.5"/><apiTool description="" name="Flex" version="4"/></apiVersion><DefaultProperty name="mxmlContent"/></asMetadata></prolog><apiClassifierDetail><apiClassifierDef><apiAccess value="public"/><apiStatic/><apiBaseInterface>mx.binding:IBindingClient</apiBaseInterface><apiBaseInterface>mx.core:IStateClient2</apiBaseInterface><apiBaseClassifier>spark.skins:SparkSkin</apiBaseClassifier></apiClassifierDef><apiDesc>The default skin class for the Spark Button component.  
</apiDesc></apiClassifierDetail><related-links><link href="" invalidHref="spark.components.Button.xml"><linktext>spark.components.Button</linktext></link></related-links><apiConstructor id="DisplayApplication.CustomSkins:CustomStartButtonSkin:CustomStartButtonSkin"><apiName>CustomStartButtonSkin</apiName><shortdesc>Constructor.</shortdesc><prolog/><apiConstructorDetail><apiConstructorDef><apiAccess value="public"/></apiConstructorDef><apiDesc>Constructor.</apiDesc></apiConstructorDetail></apiConstructor><apiValue id="DisplayApplication.CustomSkins:CustomStartButtonSkin:hostComponent"><apiName>hostComponent</apiName><shortdesc conref="spark.skins.spark.ApplicationSkin#hostComponent"> 
		</shortdesc><prolog/><apiValueDetail><apiValueDef><apiProperty isBindable="true" name="Bindable"/><apiAccess value="public"/><apiDynamic/><apiType value="spark.components:Button"/></apiValueDef><apiDesc conref="spark.skins.spark.ApplicationSkin#hostComponent"> 
		</apiDesc></apiValueDetail></apiValue><apiValue id="DisplayApplication.CustomSkins:CustomStartButtonSkin:labelDisplay"><apiName>labelDisplay</apiName><shortdesc/><prolog/><apiValueDetail><apiValueDef><apiProperty isBindable="true" name="Bindable"/><apiAccess value="public"/><apiDynamic/><apiType value="spark.components:Label"/></apiValueDef><apiDesc></apiDesc></apiValueDetail></apiValue></apiClassifier><apiClassifier id="DisplayApplication.CustomSkins:CustomDimesionButtonSkin"><apiName>CustomDimesionButtonSkin</apiName><shortdesc>The default skin class for the Spark Button component.</shortdesc><prolog><asMetadata><apiVersion><apiLanguage version="3.0"/><apiPlatform description="" name="Flash" version="10"/><apiPlatform description="" name="AIR" version="1.5"/><apiTool description="" name="Flex" version="4"/></apiVersion><DefaultProperty name="mxmlContent"/></asMetadata></prolog><apiClassifierDetail><apiClassifierDef><apiAccess value="public"/><apiStatic/><apiBaseInterface>mx.binding:IBindingClient</apiBaseInterface><apiBaseInterface>mx.core:IStateClient2</apiBaseInterface><apiBaseClassifier>spark.skins:SparkSkin</apiBaseClassifier></apiClassifierDef><apiDesc>The default skin class for the Spark Button component.  
</apiDesc></apiClassifierDetail><related-links><link href="" invalidHref="spark.components.Button.xml"><linktext>spark.components.Button</linktext></link></related-links><apiConstructor id="DisplayApplication.CustomSkins:CustomDimesionButtonSkin:CustomDimesionButtonSkin"><apiName>CustomDimesionButtonSkin</apiName><shortdesc>Constructor.</shortdesc><prolog/><apiConstructorDetail><apiConstructorDef><apiAccess value="public"/></apiConstructorDef><apiDesc>Constructor.</apiDesc></apiConstructorDetail></apiConstructor><apiValue id="DisplayApplication.CustomSkins:CustomDimesionButtonSkin:hostComponent"><apiName>hostComponent</apiName><shortdesc conref="spark.skins.spark.ApplicationSkin#hostComponent"> 
		</shortdesc><prolog/><apiValueDetail><apiValueDef><apiProperty isBindable="true" name="Bindable"/><apiAccess value="public"/><apiDynamic/><apiType value="spark.components:Button"/></apiValueDef><apiDesc conref="spark.skins.spark.ApplicationSkin#hostComponent"> 
		</apiDesc></apiValueDetail></apiValue><apiValue id="DisplayApplication.CustomSkins:CustomDimesionButtonSkin:labelDisplay"><apiName>labelDisplay</apiName><shortdesc/><prolog/><apiValueDetail><apiValueDef><apiProperty isBindable="true" name="Bindable"/><apiAccess value="public"/><apiDynamic/><apiType value="spark.components:Label"/></apiValueDef><apiDesc></apiDesc></apiValueDetail></apiValue></apiClassifier><apiClassifier id="DisplayApplication.CustomSkins:CustomRadioSkin"><apiName>CustomRadioSkin</apiName><shortdesc>The default skin class for a Spark RadioButton component.</shortdesc><prolog><asMetadata><apiVersion><apiLanguage version="3.0"/><apiPlatform description="" name="Flash" version="10"/><apiPlatform description="" name="AIR" version="1.5"/><apiTool description="" name="Flex" version="4"/></apiVersion><DefaultProperty name="mxmlContent"/></asMetadata></prolog><apiClassifierDetail><apiClassifierDef><apiAccess value="public"/><apiStatic/><apiBaseInterface>mx.core:IStateClient2</apiBaseInterface><apiBaseClassifier>spark.skins:SparkSkin</apiBaseClassifier></apiClassifierDef><apiDesc>The default skin class for a Spark RadioButton component.  
       </apiDesc></apiClassifierDetail><related-links><link href="" invalidHref="spark.components.RadioButton.xml"><linktext>spark.components.RadioButton</linktext></link><link href="" invalidHref="spark.components.RadioButtonGroup.xml"><linktext>spark.components.RadioButtonGroup</linktext></link></related-links><apiConstructor id="DisplayApplication.CustomSkins:CustomRadioSkin:CustomRadioSkin"><apiName>CustomRadioSkin</apiName><shortdesc>Constructor.</shortdesc><prolog/><apiConstructorDetail><apiConstructorDef><apiAccess value="public"/></apiConstructorDef><apiDesc>Constructor.</apiDesc></apiConstructorDetail></apiConstructor><apiValue id="DisplayApplication.CustomSkins:CustomRadioSkin:dot"><apiName>dot</apiName><shortdesc>Defines the appearance of the RadioButton's dot.</shortdesc><prolog/><apiValueDetail><apiValueDef><apiProperty isBindable="true" name="Bindable"/><apiAccess value="public"/><apiDynamic/><apiType value="spark.primitives:Ellipse"/></apiValueDef><apiDesc>Defines the appearance of the RadioButton's dot. To customize the appearance of the dot, create a custom RadioButtonSkin class.</apiDesc></apiValueDetail></apiValue><apiValue id="DisplayApplication.CustomSkins:CustomRadioSkin:hostComponent"><apiName>hostComponent</apiName><shortdesc conref="spark.skins.spark.ApplicationSkin#hostComponent"> 
         </shortdesc><prolog/><apiValueDetail><apiValueDef><apiProperty isBindable="true" name="Bindable"/><apiAccess value="public"/><apiDynamic/><apiType value="spark.components:RadioButton"/></apiValueDef><apiDesc conref="spark.skins.spark.ApplicationSkin#hostComponent"> 
         </apiDesc></apiValueDetail></apiValue></apiClassifier><apiClassifier id="DisplayApplication.CustomSkins:CustomBackButtonSkin"><apiName>CustomBackButtonSkin</apiName><shortdesc>The default skin class for the Spark Button component.</shortdesc><prolog><asMetadata><apiVersion><apiLanguage version="3.0"/><apiPlatform description="" name="Flash" version="10"/><apiPlatform description="" name="AIR" version="1.5"/><apiTool description="" name="Flex" version="4"/></apiVersion><DefaultProperty name="mxmlContent"/></asMetadata></prolog><apiClassifierDetail><apiClassifierDef><apiAccess value="public"/><apiStatic/><apiBaseInterface>mx.binding:IBindingClient</apiBaseInterface><apiBaseInterface>mx.core:IStateClient2</apiBaseInterface><apiBaseClassifier>spark.skins:SparkSkin</apiBaseClassifier></apiClassifierDef><apiDesc>The default skin class for the Spark Button component.  
</apiDesc></apiClassifierDetail><related-links><link href="" invalidHref="spark.components.Button.xml"><linktext>spark.components.Button</linktext></link></related-links><apiConstructor id="DisplayApplication.CustomSkins:CustomBackButtonSkin:CustomBackButtonSkin"><apiName>CustomBackButtonSkin</apiName><shortdesc>Constructor.</shortdesc><prolog/><apiConstructorDetail><apiConstructorDef><apiAccess value="public"/></apiConstructorDef><apiDesc>Constructor.</apiDesc></apiConstructorDetail></apiConstructor><apiValue id="DisplayApplication.CustomSkins:CustomBackButtonSkin:hostComponent"><apiName>hostComponent</apiName><shortdesc conref="spark.skins.spark.ApplicationSkin#hostComponent"> 
		</shortdesc><prolog/><apiValueDetail><apiValueDef><apiProperty isBindable="true" name="Bindable"/><apiAccess value="public"/><apiDynamic/><apiType value="spark.components:Button"/></apiValueDef><apiDesc conref="spark.skins.spark.ApplicationSkin#hostComponent"> 
		</apiDesc></apiValueDetail></apiValue><apiValue id="DisplayApplication.CustomSkins:CustomBackButtonSkin:labelDisplay"><apiName>labelDisplay</apiName><shortdesc/><prolog/><apiValueDetail><apiValueDef><apiProperty isBindable="true" name="Bindable"/><apiAccess value="public"/><apiDynamic/><apiType value="spark.components:Label"/></apiValueDef><apiDesc></apiDesc></apiValueDetail></apiValue></apiClassifier><apiClassifier id="DisplayApplication.CustomSkins:CustomEyeButtonSkin"><apiName>CustomEyeButtonSkin</apiName><shortdesc>The default skin class for the Spark Button component.</shortdesc><prolog><asMetadata><apiVersion><apiLanguage version="3.0"/><apiPlatform description="" name="Flash" version="10"/><apiPlatform description="" name="AIR" version="1.5"/><apiTool description="" name="Flex" version="4"/></apiVersion><DefaultProperty name="mxmlContent"/></asMetadata></prolog><apiClassifierDetail><apiClassifierDef><apiAccess value="public"/><apiStatic/><apiBaseInterface>mx.binding:IBindingClient</apiBaseInterface><apiBaseInterface>mx.core:IStateClient2</apiBaseInterface><apiBaseClassifier>spark.skins:SparkSkin</apiBaseClassifier></apiClassifierDef><apiDesc>The default skin class for the Spark Button component.  
       </apiDesc></apiClassifierDetail><related-links><link href="" invalidHref="spark.components.Button.xml"><linktext>spark.components.Button</linktext></link></related-links><apiConstructor id="DisplayApplication.CustomSkins:CustomEyeButtonSkin:CustomEyeButtonSkin"><apiName>CustomEyeButtonSkin</apiName><shortdesc>Constructor.</shortdesc><prolog/><apiConstructorDetail><apiConstructorDef><apiAccess value="public"/></apiConstructorDef><apiDesc>Constructor.</apiDesc></apiConstructorDetail></apiConstructor><apiValue id="DisplayApplication.CustomSkins:CustomEyeButtonSkin:hostComponent"><apiName>hostComponent</apiName><shortdesc conref="spark.skins.spark.ApplicationSkin#hostComponent"> 
		</shortdesc><prolog/><apiValueDetail><apiValueDef><apiProperty isBindable="true" name="Bindable"/><apiAccess value="public"/><apiDynamic/><apiType value="spark.components:Button"/></apiValueDef><apiDesc conref="spark.skins.spark.ApplicationSkin#hostComponent"> 
		</apiDesc></apiValueDetail></apiValue></apiClassifier><apiClassifier id="DisplayApplication.CustomSkins:CustomLoginPanelSkin"><apiName>CustomLoginPanelSkin</apiName><shortdesc>The default skin class for a Spark Panel container.</shortdesc><prolog><asMetadata><apiVersion><apiLanguage version="3.0"/><apiPlatform description="" name="Flash" version="10"/><apiPlatform description="" name="AIR" version="1.5"/><apiTool description="" name="Flex" version="4"/></apiVersion><DefaultProperty name="mxmlContent"/></asMetadata></prolog><apiClassifierDetail><apiClassifierDef><apiAccess value="public"/><apiStatic/><apiBaseInterface>mx.binding:IBindingClient</apiBaseInterface><apiBaseInterface>mx.core:IStateClient2</apiBaseInterface><apiBaseClassifier>spark.skins:SparkSkin</apiBaseClassifier></apiClassifierDef><apiDesc>The default skin class for a Spark Panel container.  
    </apiDesc></apiClassifierDetail><related-links><link href="" invalidHref="spark.components.Panel.xml"><linktext>spark.components.Panel</linktext></link></related-links><apiConstructor id="DisplayApplication.CustomSkins:CustomLoginPanelSkin:CustomLoginPanelSkin"><apiName>CustomLoginPanelSkin</apiName><shortdesc>Constructor.</shortdesc><prolog/><apiConstructorDetail><apiConstructorDef><apiAccess value="public"/></apiConstructorDef><apiDesc>Constructor.</apiDesc></apiConstructorDetail></apiConstructor><apiValue id="DisplayApplication.CustomSkins:CustomLoginPanelSkin:background"><apiName>background</apiName><shortdesc>Defines the appearance of the PanelSkin class's background.</shortdesc><prolog/><apiValueDetail><apiValueDef><apiProperty isBindable="true" name="Bindable"/><apiAccess value="public"/><apiDynamic/><apiType value="spark.primitives:Rect"/></apiValueDef><apiDesc>Defines the appearance of the PanelSkin class's background.</apiDesc></apiValueDetail></apiValue><apiValue id="DisplayApplication.CustomSkins:CustomLoginPanelSkin:contentGroup"><apiName>contentGroup</apiName><shortdesc conref="spark.components.SkinnableContainer#contentGroup"/><prolog/><apiValueDetail><apiValueDef><apiProperty isBindable="true" name="Bindable"/><apiAccess value="public"/><apiDynamic/><apiType value="spark.components:Group"/></apiValueDef><apiDesc conref="spark.components.SkinnableContainer#contentGroup"></apiDesc></apiValueDetail></apiValue><apiValue id="DisplayApplication.CustomSkins:CustomLoginPanelSkin:contents"><apiName>contents</apiName><shortdesc>Contains the vertical stack of titlebar content and controlbar.</shortdesc><prolog/><apiValueDetail><apiValueDef><apiProperty isBindable="true" name="Bindable"/><apiAccess value="public"/><apiDynamic/><apiType value="spark.components:Group"/></apiValueDef><apiDesc>Contains the vertical stack of titlebar content and controlbar.</apiDesc></apiValueDetail></apiValue><apiValue id="DisplayApplication.CustomSkins:CustomLoginPanelSkin:controlBarGroup"><apiName>controlBarGroup</apiName><shortdesc conref="spark.components.Panel#controlBarGroup"/><prolog/><apiValueDetail><apiValueDef><apiProperty isBindable="true" name="Bindable"/><apiAccess value="public"/><apiDynamic/><apiType value="spark.components:Group"/></apiValueDef><apiDesc conref="spark.components.Panel#controlBarGroup"></apiDesc></apiValueDetail></apiValue><apiValue id="DisplayApplication.CustomSkins:CustomLoginPanelSkin:hostComponent"><apiName>hostComponent</apiName><shortdesc conref="spark.skins.spark.ApplicationSkin#hostComponent"> 
         </shortdesc><prolog/><apiValueDetail><apiValueDef><apiProperty isBindable="true" name="Bindable"/><apiAccess value="public"/><apiDynamic/><apiType value="spark.components:Panel"/></apiValueDef><apiDesc conref="spark.skins.spark.ApplicationSkin#hostComponent"> 
         </apiDesc></apiValueDetail></apiValue><apiValue id="DisplayApplication.CustomSkins:CustomLoginPanelSkin:titleDisplay"><apiName>titleDisplay</apiName><shortdesc conref="spark.components.Panel#titleDisplay"/><prolog/><apiValueDetail><apiValueDef><apiProperty isBindable="true" name="Bindable"/><apiAccess value="public"/><apiDynamic/><apiType value="spark.components:Label"/></apiValueDef><apiDesc conref="spark.components.Panel#titleDisplay"></apiDesc></apiValueDetail></apiValue></apiClassifier><apiClassifier id="DisplayApplication.CustomSkins:CustomTextInputSkin"><apiName>CustomTextInputSkin</apiName><shortdesc>The default skin class for Spark TextInput component.</shortdesc><prolog><asMetadata><apiVersion><apiLanguage version="3.0"/><apiPlatform description="" name="Flash" version="10"/><apiPlatform description="" name="AIR" version="1.5"/><apiTool description="" name="Flex" version="4"/></apiVersion><DefaultProperty name="mxmlContent"/></asMetadata></prolog><apiClassifierDetail><apiClassifierDef><apiAccess value="public"/><apiStatic/><apiBaseInterface>mx.binding:IBindingClient</apiBaseInterface><apiBaseInterface>mx.core:IStateClient2</apiBaseInterface><apiBaseClassifier>spark.skins:SparkSkin</apiBaseClassifier></apiClassifierDef><apiDesc>The default skin class for Spark TextInput component.  
     </apiDesc></apiClassifierDetail><related-links><link href="" invalidHref="spark.components.TextInput.xml"><linktext>spark.components.TextInput</linktext></link></related-links><apiConstructor id="DisplayApplication.CustomSkins:CustomTextInputSkin:CustomTextInputSkin"><apiName>CustomTextInputSkin</apiName><shortdesc>Constructor.</shortdesc><prolog/><apiConstructorDetail><apiConstructorDef><apiAccess value="public"/></apiConstructorDef><apiDesc>Constructor.</apiDesc></apiConstructorDetail></apiConstructor><apiValue id="DisplayApplication.CustomSkins:CustomTextInputSkin:background"><apiName>background</apiName><shortdesc>Defines the appearance of the TextInput component's background.</shortdesc><prolog/><apiValueDetail><apiValueDef><apiProperty isBindable="true" name="Bindable"/><apiAccess value="public"/><apiDynamic/><apiType value="spark.primitives:Rect"/></apiValueDef><apiDesc>Defines the appearance of the TextInput component's background.</apiDesc></apiValueDetail></apiValue><apiValue id="DisplayApplication.CustomSkins:CustomTextInputSkin:hostComponent"><apiName>hostComponent</apiName><shortdesc conref="spark.skins.spark.ApplicationSkin#hostComponent"> 
         </shortdesc><prolog/><apiValueDetail><apiValueDef><apiProperty isBindable="true" name="Bindable"/><apiAccess value="public"/><apiDynamic/><apiType value="spark.components:TextInput"/></apiValueDef><apiDesc conref="spark.skins.spark.ApplicationSkin#hostComponent"> 
         </apiDesc></apiValueDetail></apiValue><apiValue id="DisplayApplication.CustomSkins:CustomTextInputSkin:textDisplay"><apiName>textDisplay</apiName><shortdesc conref="spark.components.supportClasses.SkinnableTextBase#textDisplay"/><prolog/><apiValueDetail><apiValueDef><apiProperty isBindable="true" name="Bindable"/><apiAccess value="public"/><apiDynamic/><apiType value="spark.components:RichEditableText"/></apiValueDef><apiDesc conref="spark.components.supportClasses.SkinnableTextBase#textDisplay"></apiDesc></apiValueDetail></apiValue></apiClassifier><apiClassifier id="DisplayApplication.CustomSkins:SoundButtonSkin"><apiName>SoundButtonSkin</apiName><shortdesc>The default skin class for the Spark Button component.</shortdesc><prolog><asMetadata><apiVersion><apiLanguage version="3.0"/><apiPlatform description="" name="Flash" version="10"/><apiPlatform description="" name="AIR" version="1.5"/><apiTool description="" name="Flex" version="4"/></apiVersion><DefaultProperty name="mxmlContent"/></asMetadata></prolog><apiClassifierDetail><apiClassifierDef><apiAccess value="public"/><apiStatic/><apiBaseInterface>mx.core:IStateClient2</apiBaseInterface><apiBaseClassifier>spark.skins:SparkSkin</apiBaseClassifier></apiClassifierDef><apiDesc>The default skin class for the Spark Button component.  
       </apiDesc></apiClassifierDetail><related-links><link href="" invalidHref="spark.components.Button.xml"><linktext>spark.components.Button</linktext></link></related-links><apiConstructor id="DisplayApplication.CustomSkins:SoundButtonSkin:SoundButtonSkin"><apiName>SoundButtonSkin</apiName><shortdesc>Constructor.</shortdesc><prolog/><apiConstructorDetail><apiConstructorDef><apiAccess value="public"/></apiConstructorDef><apiDesc>Constructor.</apiDesc></apiConstructorDetail></apiConstructor><apiValue id="DisplayApplication.CustomSkins:SoundButtonSkin:hostComponent"><apiName>hostComponent</apiName><shortdesc conref="spark.skins.spark.ApplicationSkin#hostComponent"> 
         </shortdesc><prolog/><apiValueDetail><apiValueDef><apiProperty isBindable="true" name="Bindable"/><apiAccess value="public"/><apiDynamic/><apiType value="spark.components:Button"/></apiValueDef><apiDesc conref="spark.skins.spark.ApplicationSkin#hostComponent"> 
         </apiDesc></apiValueDetail></apiValue></apiClassifier><apiClassifier id="DisplayApplication.CustomSkins:CustomLoginInputSkin"><apiName>CustomLoginInputSkin</apiName><shortdesc>The default skin class for Spark TextInput component.</shortdesc><prolog><asMetadata><apiVersion><apiLanguage version="3.0"/><apiPlatform description="" name="Flash" version="10"/><apiPlatform description="" name="AIR" version="1.5"/><apiTool description="" name="Flex" version="4"/></apiVersion><DefaultProperty name="mxmlContent"/></asMetadata></prolog><apiClassifierDetail><apiClassifierDef><apiAccess value="public"/><apiStatic/><apiBaseInterface>mx.core:IStateClient2</apiBaseInterface><apiBaseClassifier>spark.skins:SparkSkin</apiBaseClassifier></apiClassifierDef><apiDesc>The default skin class for Spark TextInput component.  
     </apiDesc></apiClassifierDetail><related-links><link href="" invalidHref="spark.components.TextInput.xml"><linktext>spark.components.TextInput</linktext></link></related-links><apiConstructor id="DisplayApplication.CustomSkins:CustomLoginInputSkin:CustomLoginInputSkin"><apiName>CustomLoginInputSkin</apiName><shortdesc>Constructor.</shortdesc><prolog/><apiConstructorDetail><apiConstructorDef><apiAccess value="public"/></apiConstructorDef><apiDesc>Constructor.</apiDesc></apiConstructorDetail></apiConstructor><apiValue id="DisplayApplication.CustomSkins:CustomLoginInputSkin:hostComponent"><apiName>hostComponent</apiName><shortdesc conref="spark.skins.spark.ApplicationSkin#hostComponent"> 
         </shortdesc><prolog/><apiValueDetail><apiValueDef><apiProperty isBindable="true" name="Bindable"/><apiAccess value="public"/><apiDynamic/><apiType value="spark.components:TextInput"/></apiValueDef><apiDesc conref="spark.skins.spark.ApplicationSkin#hostComponent"> 
         </apiDesc></apiValueDetail></apiValue><apiValue id="DisplayApplication.CustomSkins:CustomLoginInputSkin:textDisplay"><apiName>textDisplay</apiName><shortdesc conref="spark.components.supportClasses.SkinnableTextBase#textDisplay"/><prolog/><apiValueDetail><apiValueDef><apiProperty isBindable="true" name="Bindable"/><apiAccess value="public"/><apiDynamic/><apiType value="spark.components:RichEditableText"/></apiValueDef><apiDesc conref="spark.components.supportClasses.SkinnableTextBase#textDisplay"></apiDesc></apiValueDetail></apiValue></apiClassifier></apiPackage>